adminpy.py
adminpy-0.5.1.dist-info/LICENSE
adminpy-0.5.1.dist-info/METADATA
adminpy-0.5.1.dist-info/WHEEL
adminpy-0.5.1.dist-info/top_level.txt
adminpy-0.5.1.dist-info/RECORD
