Metadata-Version: 2.1
Name: adminpy
Version: 0.5.1
Summary: Admin escalator module for Python
Author: Lee Zhi Wei
License: UNKNOWN
Platform: UNKNOWN
Classifier: Programming Language :: Python :: 3
Classifier: License :: OSI Approved :: MIT License
Classifier: Operating System :: OS Independent
Requires-Python: >=3.6
License-File: LICENSE
Requires-Dist: pyuac
